Metadata-Version: 1.0
Name: phonetic-algorithmRu
Version: 0.10.1
Summary: Phonenetic algorithm for Russian language
Home-page: UNKNOWN
Author: Anastasiya Kostyanitsyna, George Moroz
Author-email: UNKNOWN
License: UNKNOWN
Platform: UNKNOWN
